nawah_cli/__init__.py
nawah_cli/__main__.py
nawah_cli/cli.py
nawah_cli-1.0.7.dist-info/LICENSE
nawah_cli-1.0.7.dist-info/METADATA
nawah_cli-1.0.7.dist-info/WHEEL
nawah_cli-1.0.7.dist-info/entry_points.txt
nawah_cli-1.0.7.dist-info/top_level.txt
nawah_cli-1.0.7.dist-info/RECORD
