Metadata-Version: 2.1
Name: nawah-cli
Version: 1.0.7
Summary: CLI for Nawah--Rapid app development framework
Home-page: https://github.com/nawah-io/nawah_cli
Author: Mahmoud Abduljawad
Author-email: mahmoud@masaar.com
License: UNKNOWN
Project-URL: Docs: Github, https://github.com/nawah-io/nawah_docs
Project-URL: GitHub: issues, https://github.com/nawah-io/nawah_cli/issues
Project-URL: GitHub: repo, https://github.com/nawah-io/nawah_cli
Platform: UNKNOWN
Classifier: Programming Language :: Python :: 3
Classifier: Programming Language :: Python :: 3.8
Classifier: Development Status :: 5 - Production/Stable
Classifier: License :: OSI Approved :: GNU General Public License v3 or later (GPLv3+)
Classifier: Operating System :: OS Independent
Classifier: Topic :: Internet :: WWW/HTTP
Classifier: Framework :: AsyncIO
Requires-Python: >=3.8
